quare/__init__.py
quare/cli.py
quare/config.py
quare/exceptions.py
quare/quare.py
quare/quip.py
quare/quip_classes.py
quare/quip_websocket.py
quare/ui_messages.py
quare/utils.py
quare-0.2.4.dist-info/entry_points.txt
quare-0.2.4.dist-info/LICENSE
quare-0.2.4.dist-info/WHEEL
quare-0.2.4.dist-info/METADATA
quare-0.2.4.dist-info/RECORD
